{"file":"reference/table-operations/update-by-operations/OperationControl.md","objects":{"source":{"type":"Table","data":{"columns":[{"name":"Letter","type":"java.lang.String"},{"name":"X","type":"double"}],"rows":[[{"value":"A"},{"value":"NaN"}],[{"value":"B"},{"value":"6.7045"}],[{"value":"A"},{"value":"3.0276"}],[{"value":"B"},{"value":"1.3070"}],[{"value":"A"},{"value":"4.5924"}],[{"value":"B"},{"value":"6.4597"}],[{"value":"A"},{"value":"2.8539"}],[{"value":"B"},{"value":"NaN"}],[{"value":"A"},{"value":"7.7120"}],[{"value":"B"},{"value":"7.7212"}],[{"value":"A"},{"value":"5.3387"}],[{"value":"B"},{"value":"1.1122"}],[{"value":"A"},{"value":"1.5150"}],[{"value":"B"},{"value":"2.0411"}],[{"value":"A"},{"value":"NaN"}],[{"value":"B"},{"value":"8.5057"}],[{"value":"A"},{"value":"9.0213"}],[{"value":"B"},{"value":"3.3778"}],[{"value":"A"},{"value":"9.8624"}],[{"value":"B"},{"value":"5.7928"}],[{"value":"A"},{"value":"9.5855"}],[{"value":"B"},{"value":"NaN"}],[{"value":"A"},{"value":"8.3538"}],[{"value":"B"},{"value":"9.9749"}],[{"value":"A"},{"value":"7.0127"}],[{"value":"B"},{"value":"9.5657"}],[{"value":"A"},{"value":"0.4748"}],[{"value":"B"},{"value":"2.2439"}],[{"value":"A"},{"value":"NaN"}],[{"value":"B"},{"value":"4.2815"}]]}},"result":{"type":"Table","data":{"columns":[{"name":"Letter","type":"java.lang.String"},{"name":"X","type":"double"},{"name":"EmaX","type":"double"}],"rows":[[{"value":"A"},{"value":"NaN"},{"value":"NaN"}],[{"value":"B"},{"value":"6.7045"},{"value":"6.7045"}],[{"value":"A"},{"value":"3.0276"},{"value":"NaN"}],[{"value":"B"},{"value":"1.3070"},{"value":"5.7261"}],[{"value":"A"},{"value":"4.5924"},{"value":"NaN"}],[{"value":"B"},{"value":"6.4597"},{"value":"5.8591"}],[{"value":"A"},{"value":"2.8539"},{"value":"NaN"}],[{"value":"B"},{"value":"NaN"},{"value":"NaN"}],[{"value":"A"},{"value":"7.7120"},{"value":"NaN"}],[{"value":"B"},{"value":"7.7212"},{"value":"NaN"}],[{"value":"A"},{"value":"5.3387"},{"value":"NaN"}],[{"value":"B"},{"value":"1.1122"},{"value":"NaN"}],[{"value":"A"},{"value":"1.5150"},{"value":"NaN"}],[{"value":"B"},{"value":"2.0411"},{"value":"NaN"}],[{"value":"A"},{"value":"NaN"},{"value":"NaN"}],[{"value":"B"},{"value":"8.5057"},{"value":"NaN"}],[{"value":"A"},{"value":"9.0213"},{"value":"NaN"}],[{"value":"B"},{"value":"3.3778"},{"value":"NaN"}],[{"value":"A"},{"value":"9.8624"},{"value":"NaN"}],[{"value":"B"},{"value":"5.7928"},{"value":"NaN"}],[{"value":"A"},{"value":"9.5855"},{"value":"NaN"}],[{"value":"B"},{"value":"NaN"},{"value":"NaN"}],[{"value":"A"},{"value":"8.3538"},{"value":"NaN"}],[{"value":"B"},{"value":"9.9749"},{"value":"NaN"}],[{"value":"A"},{"value":"7.0127"},{"value":"NaN"}],[{"value":"B"},{"value":"9.5657"},{"value":"NaN"}],[{"value":"A"},{"value":"0.4748"},{"value":"NaN"}],[{"value":"B"},{"value":"2.2439"},{"value":"NaN"}],[{"value":"A"},{"value":"NaN"},{"value":"NaN"}],[{"value":"B"},{"value":"4.2815"},{"value":"NaN"}]]}}}}