{"file":"reference/query-language/control-flow/casting.md","objects":{"source":{"type":"Table","data":{"columns":[{"name":"X","type":"java.lang.String"}],"rows":[[{"value":"[0.7140013663130906,0.8791106869694261,0.7612842380623389]"}],[{"value":"[0.8836726169551584,0.18826010849597996,0.021956849372910092]"}],[{"value":"[0.47126785068674215,0.08294727931000101,0.7605918027952067]"}],[{"value":"[0.6917815996158365,0.3297741376060104,0.07477169695629582]"}],[{"value":"[0.5311491801636187,0.8884592910006707,0.4007557385467636]"}]]}},"source_meta":{"type":"Table","data":{"columns":[{"name":"Name","type":"java.lang.String"},{"name":"DataType","type":"java.lang.String"},{"name":"ColumnType","type":"java.lang.String"},{"name":"IsPartitioning","type":"java.lang.Boolean"}],"rows":[[{"value":"X"},{"value":"double[]"},{"value":"Normal"},{"value":"false"}]]}}}}