{"file":"reference/table-operations/update-by-operations/em-max.md","objects":{"source":{"type":"Table","data":{"columns":[{"name":"Timestamp","type":"java.time.Instant"},{"name":"Letter","type":"java.lang.String"},{"name":"X","type":"int"}],"rows":[[{"value":"2023-01-01 00:00:00.000"},{"value":"A"},{"value":"18"}],[{"value":"2023-01-01 00:00:01.000"},{"value":"B"},{"value":"0"}],[{"value":"2023-01-01 00:00:02.000"},{"value":"A"},{"value":"14"}],[{"value":"2023-01-01 00:00:03.000"},{"value":"B"},{"value":"11"}],[{"value":"2023-01-01 00:00:04.000"},{"value":"A"},{"value":"5"}],[{"value":"2023-01-01 00:00:05.000"},{"value":"B"},{"value":"20"}],[{"value":"2023-01-01 00:00:06.000"},{"value":"A"},{"value":"10"}],[{"value":"2023-01-01 00:00:07.000"},{"value":"B"},{"value":"17"}],[{"value":"2023-01-01 00:00:08.000"},{"value":"A"},{"value":"23"}],[{"value":"2023-01-01 00:00:09.000"},{"value":"B"},{"value":"10"}]]}},"result":{"type":"Table","data":{"columns":[{"name":"Timestamp","type":"java.time.Instant"},{"name":"Letter","type":"java.lang.String"},{"name":"X","type":"int"},{"name":"EmMax_Tick_X","type":"double"},{"name":"EmMax_Time_X","type":"double"}],"rows":[[{"value":"2023-01-01 00:00:00.000"},{"value":"A"},{"value":"18"},{"value":"18.0000"},{"value":"18.0000"}],[{"value":"2023-01-01 00:00:01.000"},{"value":"B"},{"value":"0"},{"value":"14.7372"},{"value":"14.7372"}],[{"value":"2023-01-01 00:00:02.000"},{"value":"A"},{"value":"14"},{"value":"14.0000"},{"value":"14.0000"}],[{"value":"2023-01-01 00:00:03.000"},{"value":"B"},{"value":"11"},{"value":"11.4622"},{"value":"11.4622"}],[{"value":"2023-01-01 00:00:04.000"},{"value":"A"},{"value":"5"},{"value":"9.3845"},{"value":"9.3845"}],[{"value":"2023-01-01 00:00:05.000"},{"value":"B"},{"value":"20"},{"value":"20.0000"},{"value":"20.0000"}],[{"value":"2023-01-01 00:00:06.000"},{"value":"A"},{"value":"10"},{"value":"16.3746"},{"value":"16.3746"}],[{"value":"2023-01-01 00:00:07.000"},{"value":"B"},{"value":"17"},{"value":"17.0000"},{"value":"17.0000"}],[{"value":"2023-01-01 00:00:08.000"},{"value":"A"},{"value":"23"},{"value":"23.0000"},{"value":"23.0000"}],[{"value":"2023-01-01 00:00:09.000"},{"value":"B"},{"value":"10"},{"value":"18.8308"},{"value":"18.8308"}]]}}}}