{"file":"reference/cheat-sheets/cheat-sheet.md","objects":{"countOfEntireTable":{"type":"Table","data":{"columns":[{"name":"Count","type":"long"}],"rows":[[{"value":"26,300"}]]}},"countOfGroup":{"type":"Table","data":{"columns":[{"name":"String1","type":"java.lang.String"},{"name":"N","type":"long"}],"rows":[[{"value":"X"},{"value":"1,023"}],[{"value":"Z"},{"value":"990"}],[{"value":"U"},{"value":"1,035"}],[{"value":"H"},{"value":"974"}],[{"value":"M"},{"value":"984"}],[{"value":"V"},{"value":"999"}],[{"value":"F"},{"value":"1,006"}],[{"value":"Q"},{"value":"992"}],[{"value":"G"},{"value":"973"}],[{"value":"D"},{"value":"1,035"}],[{"value":"Y"},{"value":"1,074"}],[{"value":"O"},{"value":"977"}],[{"value":"W"},{"value":"1,009"}],[{"value":"B"},{"value":"1,006"}],[{"value":"C"},{"value":"982"}],[{"value":"E"},{"value":"1,048"}],[{"value":"J"},{"value":"1,029"}],[{"value":"T"},{"value":"1,045"}],[{"value":"R"},{"value":"1,030"}],[{"value":"A"},{"value":"1,035"}],[{"value":"P"},{"value":"1,056"}],[{"value":"K"},{"value":"956"}],[{"value":"S"},{"value":"1,032"}],[{"value":"L"},{"value":"994"}],[{"value":"N"},{"value":"1,004"}],[{"value":"I"},{"value":"1,012"}]]}},"firstOfGroup":{"type":"Table","data":{"columns":[{"name":"String1","type":"java.lang.String"},{"name":"X","type":"long"},{"name":"Double1","type":"double"},{"name":"Int1","type":"int"},{"name":"Timestamp","type":"java.time.Instant"},{"name":"Date","type":"java.lang.String"},{"name":"String2","type":"java.lang.String"}],"rows":[[{"value":"X"},{"value":"0"},{"value":"85.1690"},{"value":"4"},{"value":"2016-01-01 01:00:00.000"},{"value":"2016-01-01T06:00:00Z"},{"value":"umc"}],[{"value":"Z"},{"value":"1"},{"value":"11.0839"},{"value":"61"},{"value":"2016-01-01 02:00:00.000"},{"value":"2016-01-01T07:00:00Z"},{"value":"qc"}],[{"value":"U"},{"value":"2"},{"value":"10.9124"},{"value":"73"},{"value":"2016-01-01 03:00:00.000"},{"value":"2016-01-01T08:00:00Z"},{"value":"Mpk"}],[{"value":"H"},{"value":"3"},{"value":"24.4702"},{"value":"83"},{"value":"2016-01-01 04:00:00.000"},{"value":"2016-01-01T09:00:00Z"},{"value":"D"}],[{"value":"M"},{"value":"4"},{"value":"3.4423"},{"value":"11"},{"value":"2016-01-01 05:00:00.000"},{"value":"2016-01-01T10:00:00Z"},{"value":"fR"}],[{"value":"V"},{"value":"5"},{"value":"35.3742"},{"value":"53"},{"value":"2016-01-01 06:00:00.000"},{"value":"2016-01-01T11:00:00Z"},{"value":"fOG"}],[{"value":"F"},{"value":"6"},{"value":"14.9303"},{"value":"88"},{"value":"2016-01-01 07:00:00.000"},{"value":"2016-01-01T12:00:00Z"},{"value":"UgB"}],[{"value":"Q"},{"value":"8"},{"value":"40.6196"},{"value":"2"},{"value":"2016-01-01 09:00:00.000"},{"value":"2016-01-01T14:00:00Z"},{"value":"U"}],[{"value":"G"},{"value":"9"},{"value":"88.7925"},{"value":"19"},{"value":"2016-01-01 10:00:00.000"},{"value":"2016-01-01T15:00:00Z"},{"value":"Wn"}],[{"value":"D"},{"value":"12"},{"value":"52.4167"},{"value":"61"},{"value":"2016-01-01 13:00:00.000"},{"value":"2016-01-01T18:00:00Z"},{"value":"m"}],[{"value":"Y"},{"value":"15"},{"value":"15.5978"},{"value":"87"},{"value":"2016-01-01 16:00:00.000"},{"value":"2016-01-01T21:00:00Z"},{"value":"W"}],[{"value":"O"},{"value":"17"},{"value":"83.5282"},{"value":"75"},{"value":"2016-01-01 18:00:00.000"},{"value":"2016-01-01T23:00:00Z"},{"value":"H"}],[{"value":"W"},{"value":"21"},{"value":"96.5447"},{"value":"58"},{"value":"2016-01-01 22:00:00.000"},{"value":"2016-01-02T03:00:00Z"},{"value":"BDQ"}],[{"value":"B"},{"value":"23"},{"value":"6.1464"},{"value":"73"},{"value":"2016-01-02 00:00:00.000"},{"value":"2016-01-02T05:00:00Z"},{"value":"B"}],[{"value":"C"},{"value":"24"},{"value":"27.7836"},{"value":"95"},{"value":"2016-01-02 01:00:00.000"},{"value":"2016-01-02T06:00:00Z"},{"value":"T"}],[{"value":"E"},{"value":"25"},{"value":"33.8398"},{"value":"52"},{"value":"2016-01-02 02:00:00.000"},{"value":"2016-01-02T07:00:00Z"},{"value":"koA"}],[{"value":"J"},{"value":"29"},{"value":"29.7522"},{"value":"23"},{"value":"2016-01-02 06:00:00.000"},{"value":"2016-01-02T11:00:00Z"},{"value":"Lf"}],[{"value":"T"},{"value":"31"},{"value":"10.7447"},{"value":"84"},{"value":"2016-01-02 08:00:00.000"},{"value":"2016-01-02T13:00:00Z"},{"value":"s"}],[{"value":"R"},{"value":"33"},{"value":"87.6146"},{"value":"8"},{"value":"2016-01-02 10:00:00.000"},{"value":"2016-01-02T15:00:00Z"},{"value":"kI"}],[{"value":"A"},{"value":"37"},{"value":"31.3361"},{"value":"8"},{"value":"2016-01-02 14:00:00.000"},{"value":"2016-01-02T19:00:00Z"},{"value":"bU"}],[{"value":"P"},{"value":"44"},{"value":"68.5309"},{"value":"94"},{"value":"2016-01-02 21:00:00.000"},{"value":"2016-01-03T02:00:00Z"},{"value":"W"}],[{"value":"K"},{"value":"66"},{"value":"69.5251"},{"value":"87"},{"value":"2016-01-03 19:00:00.000"},{"value":"2016-01-04T00:00:00Z"},{"value":"eln"}],[{"value":"S"},{"value":"75"},{"value":"83.3481"},{"value":"43"},{"value":"2016-01-04 04:00:00.000"},{"value":"2016-01-04T09:00:00Z"},{"value":"sM"}],[{"value":"L"},{"value":"84"},{"value":"46.7948"},{"value":"97"},{"value":"2016-01-04 13:00:00.000"},{"value":"2016-01-04T18:00:00Z"},{"value":"xKO"}],[{"value":"N"},{"value":"96"},{"value":"94.5241"},{"value":"36"},{"value":"2016-01-05 01:00:00.000"},{"value":"2016-01-05T06:00:00Z"},{"value":"Y"}],[{"value":"I"},{"value":"104"},{"value":"94.0340"},{"value":"58"},{"value":"2016-01-05 09:00:00.000"},{"value":"2016-01-05T14:00:00Z"},{"value":"xA"}]]}},"lastOfGroup":{"type":"Table","data":{"columns":[{"name":"String1","type":"java.lang.String"},{"name":"X","type":"long"},{"name":"Double1","type":"double"},{"name":"Int1","type":"int"},{"name":"Timestamp","type":"java.time.Instant"},{"name":"Date","type":"java.lang.String"},{"name":"String2","type":"java.lang.String"}],"rows":[[{"value":"X"},{"value":"26,225"},{"value":"6.6552"},{"value":"19"},{"value":"2018-12-28 18:00:00.000"},{"value":"2018-12-28T23:00:00Z"},{"value":"t"}],[{"value":"Z"},{"value":"26,291"},{"value":"30.5190"},{"value":"25"},{"value":"2018-12-31 12:00:00.000"},{"value":"2018-12-31T17:00:00Z"},{"value":"rN"}],[{"value":"U"},{"value":"26,292"},{"value":"62.3181"},{"value":"46"},{"value":"2018-12-31 13:00:00.000"},{"value":"2018-12-31T18:00:00Z"},{"value":"S"}],[{"value":"H"},{"value":"26,281"},{"value":"35.1794"},{"value":"80"},{"value":"2018-12-31 02:00:00.000"},{"value":"2018-12-31T07:00:00Z"},{"value":"Y"}],[{"value":"M"},{"value":"26,296"},{"value":"21.6854"},{"value":"39"},{"value":"2018-12-31 17:00:00.000"},{"value":"2018-12-31T22:00:00Z"},{"value":"AGU"}],[{"value":"V"},{"value":"26,260"},{"value":"55.6243"},{"value":"57"},{"value":"2018-12-30 05:00:00.000"},{"value":"2018-12-30T10:00:00Z"},{"value":"ob"}],[{"value":"F"},{"value":"26,241"},{"value":"45.3834"},{"value":"46"},{"value":"2018-12-29 10:00:00.000"},{"value":"2018-12-29T15:00:00Z"},{"value":"aDT"}],[{"value":"Q"},{"value":"26,298"},{"value":"86.4751"},{"value":"47"},{"value":"2018-12-31 19:00:00.000"},{"value":"2019-01-01T00:00:00Z"},{"value":"sXk"}],[{"value":"G"},{"value":"26,265"},{"value":"66.1241"},{"value":"89"},{"value":"2018-12-30 10:00:00.000"},{"value":"2018-12-30T15:00:00Z"},{"value":"Bm"}],[{"value":"D"},{"value":"26,297"},{"value":"1.8654"},{"value":"32"},{"value":"2018-12-31 18:00:00.000"},{"value":"2018-12-31T23:00:00Z"},{"value":"T"}],[{"value":"Y"},{"value":"26,247"},{"value":"70.4306"},{"value":"51"},{"value":"2018-12-29 16:00:00.000"},{"value":"2018-12-29T21:00:00Z"},{"value":"vK"}],[{"value":"O"},{"value":"26,299"},{"value":"27.7560"},{"value":"37"},{"value":"2018-12-31 20:00:00.000"},{"value":"2019-01-01T01:00:00Z"},{"value":"P"}],[{"value":"W"},{"value":"26,258"},{"value":"94.7411"},{"value":"86"},{"value":"2018-12-30 03:00:00.000"},{"value":"2018-12-30T08:00:00Z"},{"value":"QRS"}],[{"value":"B"},{"value":"26,294"},{"value":"17.9600"},{"value":"69"},{"value":"2018-12-31 15:00:00.000"},{"value":"2018-12-31T20:00:00Z"},{"value":"sE"}],[{"value":"C"},{"value":"26,276"},{"value":"17.7775"},{"value":"12"},{"value":"2018-12-30 21:00:00.000"},{"value":"2018-12-31T02:00:00Z"},{"value":"O"}],[{"value":"E"},{"value":"26,283"},{"value":"26.4902"},{"value":"85"},{"value":"2018-12-31 04:00:00.000"},{"value":"2018-12-31T09:00:00Z"},{"value":"gYp"}],[{"value":"J"},{"value":"26,295"},{"value":"66.7462"},{"value":"63"},{"value":"2018-12-31 16:00:00.000"},{"value":"2018-12-31T21:00:00Z"},{"value":"K"}],[{"value":"T"},{"value":"26,274"},{"value":"38.2545"},{"value":"14"},{"value":"2018-12-30 19:00:00.000"},{"value":"2018-12-31T00:00:00Z"},{"value":"Sv"}],[{"value":"R"},{"value":"26,268"},{"value":"93.3369"},{"value":"85"},{"value":"2018-12-30 13:00:00.000"},{"value":"2018-12-30T18:00:00Z"},{"value":"a"}],[{"value":"A"},{"value":"26,288"},{"value":"5.7848"},{"value":"48"},{"value":"2018-12-31 09:00:00.000"},{"value":"2018-12-31T14:00:00Z"},{"value":"KR"}],[{"value":"P"},{"value":"26,277"},{"value":"44.6699"},{"value":"80"},{"value":"2018-12-30 22:00:00.000"},{"value":"2018-12-31T03:00:00Z"},{"value":"R"}],[{"value":"K"},{"value":"26,280"},{"value":"65.0330"},{"value":"71"},{"value":"2018-12-31 01:00:00.000"},{"value":"2018-12-31T06:00:00Z"},{"value":"Iv"}],[{"value":"S"},{"value":"26,284"},{"value":"7.2435"},{"value":"40"},{"value":"2018-12-31 05:00:00.000"},{"value":"2018-12-31T10:00:00Z"},{"value":"Tx"}],[{"value":"L"},{"value":"26,273"},{"value":"97.8971"},{"value":"42"},{"value":"2018-12-30 18:00:00.000"},{"value":"2018-12-30T23:00:00Z"},{"value":"fwL"}],[{"value":"N"},{"value":"26,286"},{"value":"52.5923"},{"value":"83"},{"value":"2018-12-31 07:00:00.000"},{"value":"2018-12-31T12:00:00Z"},{"value":"J"}],[{"value":"I"},{"value":"26,290"},{"value":"99.7103"},{"value":"22"},{"value":"2018-12-31 11:00:00.000"},{"value":"2018-12-31T16:00:00Z"},{"value":"X"}]]}},"sumOfGroup":{"type":"Table","data":{"columns":[{"name":"String1","type":"java.lang.String"},{"name":"Double1","type":"double"}],"rows":[[{"value":"X"},{"value":"51,765.1114"}],[{"value":"Z"},{"value":"50,902.7085"}],[{"value":"U"},{"value":"53,632.9191"}],[{"value":"H"},{"value":"48,389.1125"}],[{"value":"M"},{"value":"50,503.1534"}],[{"value":"V"},{"value":"49,798.7206"}],[{"value":"F"},{"value":"50,657.0721"}],[{"value":"Q"},{"value":"50,441.8345"}],[{"value":"G"},{"value":"48,639.3436"}],[{"value":"D"},{"value":"52,850.5099"}],[{"value":"Y"},{"value":"52,952.4703"}],[{"value":"O"},{"value":"50,283.2869"}],[{"value":"W"},{"value":"50,389.5512"}],[{"value":"B"},{"value":"51,341.3115"}],[{"value":"C"},{"value":"49,481.8798"}],[{"value":"E"},{"value":"50,289.7801"}],[{"value":"J"},{"value":"53,401.6991"}],[{"value":"T"},{"value":"53,809.9649"}],[{"value":"R"},{"value":"51,804.2970"}],[{"value":"A"},{"value":"51,578.0797"}],[{"value":"P"},{"value":"53,066.5751"}],[{"value":"K"},{"value":"48,269.2943"}],[{"value":"S"},{"value":"52,446.0046"}],[{"value":"L"},{"value":"50,343.8788"}],[{"value":"N"},{"value":"51,450.0025"}],[{"value":"I"},{"value":"52,110.7157"}]]}},"avgOfGroup":{"type":"Table","data":{"columns":[{"name":"String1","type":"java.lang.String"},{"name":"Double1","type":"double"},{"name":"Int1","type":"double"}],"rows":[[{"value":"X"},{"value":"50.6013"},{"value":"50.2561"}],[{"value":"Z"},{"value":"51.4169"},{"value":"50.6121"}],[{"value":"U"},{"value":"51.8192"},{"value":"50.6271"}],[{"value":"H"},{"value":"49.6808"},{"value":"49.6273"}],[{"value":"M"},{"value":"51.3243"},{"value":"50.7774"}],[{"value":"V"},{"value":"49.8486"},{"value":"49.3453"}],[{"value":"F"},{"value":"50.3549"},{"value":"48.8877"}],[{"value":"Q"},{"value":"50.8486"},{"value":"50.1956"}],[{"value":"G"},{"value":"49.9890"},{"value":"50.5190"}],[{"value":"D"},{"value":"51.0633"},{"value":"49.2870"}],[{"value":"Y"},{"value":"49.3040"},{"value":"49.9451"}],[{"value":"O"},{"value":"51.4670"},{"value":"49.4207"}],[{"value":"W"},{"value":"49.9401"},{"value":"49.7096"}],[{"value":"B"},{"value":"51.0351"},{"value":"50.8410"}],[{"value":"C"},{"value":"50.3889"},{"value":"50.8432"}],[{"value":"E"},{"value":"47.9864"},{"value":"51.3531"}],[{"value":"J"},{"value":"51.8967"},{"value":"49.9388"}],[{"value":"T"},{"value":"51.4928"},{"value":"51.4852"}],[{"value":"R"},{"value":"50.2954"},{"value":"51.3718"}],[{"value":"A"},{"value":"49.8339"},{"value":"48.4077"}],[{"value":"P"},{"value":"50.2524"},{"value":"50.0900"}],[{"value":"K"},{"value":"50.4909"},{"value":"48.5711"}],[{"value":"S"},{"value":"50.8198"},{"value":"49.8702"}],[{"value":"L"},{"value":"50.6478"},{"value":"50.3773"}],[{"value":"N"},{"value":"51.2450"},{"value":"48.8446"}],[{"value":"I"},{"value":"51.4928"},{"value":"49.7579"}]]}},"stdOfGroup":{"type":"Table","data":{"columns":[{"name":"String1","type":"java.lang.String"},{"name":"Double1","type":"double"},{"name":"Int1","type":"double"}],"rows":[[{"value":"X"},{"value":"28.5178"},{"value":"27.9887"}],[{"value":"Z"},{"value":"28.5795"},{"value":"27.8988"}],[{"value":"U"},{"value":"28.5194"},{"value":"28.7494"}],[{"value":"H"},{"value":"28.5741"},{"value":"28.4529"}],[{"value":"M"},{"value":"29.2047"},{"value":"29.4053"}],[{"value":"V"},{"value":"28.4899"},{"value":"28.4972"}],[{"value":"F"},{"value":"28.8302"},{"value":"28.2488"}],[{"value":"Q"},{"value":"28.6253"},{"value":"28.5576"}],[{"value":"G"},{"value":"29.4734"},{"value":"28.9037"}],[{"value":"D"},{"value":"28.2801"},{"value":"28.6231"}],[{"value":"Y"},{"value":"28.7784"},{"value":"27.9246"}],[{"value":"O"},{"value":"28.7674"},{"value":"28.6176"}],[{"value":"W"},{"value":"28.4422"},{"value":"28.9261"}],[{"value":"B"},{"value":"28.8352"},{"value":"28.8350"}],[{"value":"C"},{"value":"28.8430"},{"value":"27.9783"}],[{"value":"E"},{"value":"28.2493"},{"value":"27.9436"}],[{"value":"J"},{"value":"29.4381"},{"value":"28.7430"}],[{"value":"T"},{"value":"28.7183"},{"value":"29.3472"}],[{"value":"R"},{"value":"28.8205"},{"value":"28.2698"}],[{"value":"A"},{"value":"28.5874"},{"value":"28.7971"}],[{"value":"P"},{"value":"28.7585"},{"value":"28.8566"}],[{"value":"K"},{"value":"28.9015"},{"value":"28.6887"}],[{"value":"S"},{"value":"28.5586"},{"value":"29.4623"}],[{"value":"L"},{"value":"28.8304"},{"value":"28.7669"}],[{"value":"N"},{"value":"28.2466"},{"value":"27.7034"}],[{"value":"I"},{"value":"28.7983"},{"value":"28.7125"}]]}},"varOfGroup":{"type":"Table","data":{"columns":[{"name":"String1","type":"java.lang.String"},{"name":"Double1","type":"double"},{"name":"Int1","type":"double"}],"rows":[[{"value":"X"},{"value":"813.2668"},{"value":"783.3668"}],[{"value":"Z"},{"value":"816.7903"},{"value":"778.3448"}],[{"value":"U"},{"value":"813.3546"},{"value":"826.5262"}],[{"value":"H"},{"value":"816.4806"},{"value":"809.5681"}],[{"value":"M"},{"value":"852.9119"},{"value":"864.6696"}],[{"value":"V"},{"value":"811.6754"},{"value":"812.0880"}],[{"value":"F"},{"value":"831.1803"},{"value":"797.9963"}],[{"value":"Q"},{"value":"819.4092"},{"value":"815.5379"}],[{"value":"G"},{"value":"868.6784"},{"value":"835.4227"}],[{"value":"D"},{"value":"799.7643"},{"value":"819.2802"}],[{"value":"Y"},{"value":"828.1975"},{"value":"779.7817"}],[{"value":"O"},{"value":"827.5609"},{"value":"818.9653"}],[{"value":"W"},{"value":"808.9609"},{"value":"836.7182"}],[{"value":"B"},{"value":"831.4690"},{"value":"831.4573"}],[{"value":"C"},{"value":"831.9163"},{"value":"782.7827"}],[{"value":"E"},{"value":"798.0204"},{"value":"780.8475"}],[{"value":"J"},{"value":"866.6007"},{"value":"826.1606"}],[{"value":"T"},{"value":"824.7389"},{"value":"861.2558"}],[{"value":"R"},{"value":"830.6223"},{"value":"799.1842"}],[{"value":"A"},{"value":"817.2395"},{"value":"829.2746"}],[{"value":"P"},{"value":"827.0512"},{"value":"832.7056"}],[{"value":"K"},{"value":"835.2965"},{"value":"823.0431"}],[{"value":"S"},{"value":"815.5965"},{"value":"868.0258"}],[{"value":"L"},{"value":"831.1940"},{"value":"827.5323"}],[{"value":"N"},{"value":"797.8713"},{"value":"767.4773"}],[{"value":"I"},{"value":"829.3406"},{"value":"824.4092"}]]}},"medianOfGroup":{"type":"Table","data":{"columns":[{"name":"String1","type":"java.lang.String"},{"name":"Double1","type":"double"},{"name":"Int1","type":"double"}],"rows":[[{"value":"X"},{"value":"50.4043"},{"value":"50.0000"}],[{"value":"Z"},{"value":"51.8476"},{"value":"51.0000"}],[{"value":"U"},{"value":"51.3222"},{"value":"50.0000"}],[{"value":"H"},{"value":"50.3614"},{"value":"49.0000"}],[{"value":"M"},{"value":"51.9883"},{"value":"50.5000"}],[{"value":"V"},{"value":"48.6558"},{"value":"50.0000"}],[{"value":"F"},{"value":"50.9766"},{"value":"49.0000"}],[{"value":"Q"},{"value":"51.3240"},{"value":"50.0000"}],[{"value":"G"},{"value":"49.3450"},{"value":"50.0000"}],[{"value":"D"},{"value":"51.5519"},{"value":"50.0000"}],[{"value":"Y"},{"value":"48.6496"},{"value":"50.0000"}],[{"value":"O"},{"value":"51.7832"},{"value":"48.0000"}],[{"value":"W"},{"value":"49.7882"},{"value":"49.0000"}],[{"value":"B"},{"value":"51.1416"},{"value":"51.0000"}],[{"value":"C"},{"value":"49.7259"},{"value":"52.0000"}],[{"value":"E"},{"value":"46.0925"},{"value":"52.0000"}],[{"value":"J"},{"value":"51.9506"},{"value":"51.0000"}],[{"value":"T"},{"value":"53.0495"},{"value":"53.0000"}],[{"value":"R"},{"value":"49.9270"},{"value":"50.5000"}],[{"value":"A"},{"value":"49.0252"},{"value":"47.0000"}],[{"value":"P"},{"value":"50.3884"},{"value":"51.0000"}],[{"value":"K"},{"value":"48.9377"},{"value":"47.5000"}],[{"value":"S"},{"value":"51.6476"},{"value":"49.0000"}],[{"value":"L"},{"value":"50.9142"},{"value":"51.0000"}],[{"value":"N"},{"value":"53.6187"},{"value":"48.0000"}],[{"value":"I"},{"value":"52.3933"},{"value":"49.0000"}]]}},"minOfGroup":{"type":"Table","data":{"columns":[{"name":"String1","type":"java.lang.String"},{"name":"Double1","type":"double"},{"name":"Int1","type":"int"}],"rows":[[{"value":"X"},{"value":"1.1316"},{"value":"1"}],[{"value":"Z"},{"value":"1.0667"},{"value":"1"}],[{"value":"U"},{"value":"1.3059"},{"value":"1"}],[{"value":"H"},{"value":"1.0563"},{"value":"1"}],[{"value":"M"},{"value":"1.1898"},{"value":"1"}],[{"value":"V"},{"value":"1.0648"},{"value":"1"}],[{"value":"F"},{"value":"1.0365"},{"value":"1"}],[{"value":"Q"},{"value":"1.0255"},{"value":"1"}],[{"value":"G"},{"value":"1.1667"},{"value":"1"}],[{"value":"D"},{"value":"1.0020"},{"value":"1"}],[{"value":"Y"},{"value":"1.0409"},{"value":"1"}],[{"value":"O"},{"value":"1.0475"},{"value":"1"}],[{"value":"W"},{"value":"1.3525"},{"value":"1"}],[{"value":"B"},{"value":"1.1588"},{"value":"1"}],[{"value":"C"},{"value":"1.1842"},{"value":"1"}],[{"value":"E"},{"value":"1.0795"},{"value":"1"}],[{"value":"J"},{"value":"1.0122"},{"value":"1"}],[{"value":"T"},{"value":"1.0292"},{"value":"1"}],[{"value":"R"},{"value":"1.2212"},{"value":"1"}],[{"value":"A"},{"value":"1.2897"},{"value":"1"}],[{"value":"P"},{"value":"1.0097"},{"value":"1"}],[{"value":"K"},{"value":"1.0219"},{"value":"1"}],[{"value":"S"},{"value":"1.1260"},{"value":"1"}],[{"value":"L"},{"value":"1.1847"},{"value":"1"}],[{"value":"N"},{"value":"1.1083"},{"value":"1"}],[{"value":"I"},{"value":"1.0917"},{"value":"1"}]]}},"maxOfGroup":{"type":"Table","data":{"columns":[{"name":"String1","type":"java.lang.String"},{"name":"Double1","type":"double"},{"name":"Int1","type":"int"}],"rows":[[{"value":"X"},{"value":"99.8512"},{"value":"99"}],[{"value":"Z"},{"value":"99.8878"},{"value":"99"}],[{"value":"U"},{"value":"99.9263"},{"value":"99"}],[{"value":"H"},{"value":"99.9182"},{"value":"99"}],[{"value":"M"},{"value":"99.9964"},{"value":"99"}],[{"value":"V"},{"value":"99.9533"},{"value":"99"}],[{"value":"F"},{"value":"99.8041"},{"value":"99"}],[{"value":"Q"},{"value":"99.7797"},{"value":"99"}],[{"value":"G"},{"value":"99.9479"},{"value":"99"}],[{"value":"D"},{"value":"99.9588"},{"value":"99"}],[{"value":"Y"},{"value":"99.9874"},{"value":"99"}],[{"value":"O"},{"value":"99.8766"},{"value":"99"}],[{"value":"W"},{"value":"99.9219"},{"value":"99"}],[{"value":"B"},{"value":"99.9859"},{"value":"99"}],[{"value":"C"},{"value":"99.9438"},{"value":"99"}],[{"value":"E"},{"value":"99.9485"},{"value":"99"}],[{"value":"J"},{"value":"99.8589"},{"value":"99"}],[{"value":"T"},{"value":"99.9881"},{"value":"99"}],[{"value":"R"},{"value":"99.9566"},{"value":"99"}],[{"value":"A"},{"value":"99.9899"},{"value":"99"}],[{"value":"P"},{"value":"99.9516"},{"value":"99"}],[{"value":"K"},{"value":"99.8811"},{"value":"99"}],[{"value":"S"},{"value":"99.9457"},{"value":"99"}],[{"value":"L"},{"value":"99.8541"},{"value":"99"}],[{"value":"N"},{"value":"99.7852"},{"value":"99"}],[{"value":"I"},{"value":"99.9475"},{"value":"99"}]]}}}}